vidyo/__init__.py
vidyo/channel.py
vidyo/client.py
vidyo/errors.py
vidyo/video.py
vidyo-0.1.0.dist-info/LICENSE
vidyo-0.1.0.dist-info/METADATA
vidyo-0.1.0.dist-info/WHEEL
vidyo-0.1.0.dist-info/top_level.txt
vidyo-0.1.0.dist-info/RECORD
