Metadata-Version: 2.1
Name: vidyo
Version: 0.1.0
Summary: A simple way to get information on YouTube videos.
Home-page: https://github.com/parafoxia/vidyo
Author: Ethan Henderson
License: BSD-3-Clause
Project-URL: Documentation, https://vidyo.readthedocs.io/en/latest/
Project-URL: Source, https://github.com/parafoxia/vidyo
Project-URL: Bug Tracker, https://github.com/parafoxia/vidyo/issues
Platform: UNKNOWN
Classifier: Development Status :: 5 - Production/Stable
Classifier: Environment :: Console
Classifier: Intended Audience :: Developers
Classifier: License :: OSI Approved :: BSD License
Classifier: Natural Language :: English
Classifier: Operating System :: MacOS
Classifier: Operating System :: Microsoft :: Windows
Classifier: Operating System :: POSIX
Classifier: Operating System :: Unix
Classifier: Programming Language :: Python :: 3
Classifier: Programming Language :: Python :: 3 :: Only
Classifier: Programming Language :: Python :: 3.7
Classifier: Programming Language :: Python :: 3.8
Classifier: Programming Language :: Python :: 3.9
Classifier: Topic :: Utilities
Requires-Python: >=3.7.0
License-File: LICENSE
Requires-Dist: requests (<3,>=2)
Requires-Dist: pillow (<9,>=8)
Provides-Extra: dev
Requires-Dist: black (==21.6b0) ; extra == 'dev'
Requires-Dist: mypy (==0.910) ; extra == 'dev'
Requires-Dist: nox (==2021.6.12) ; extra == 'dev'
Requires-Dist: sphinx (==4.0.3) ; extra == 'dev'
Requires-Dist: sphinx-rtd-dark-mode (==1.2.2) ; extra == 'dev'
Requires-Dist: sphinx-rtd-theme (==0.5.2) ; extra == 'dev'
